stefan_utils/__init__.py
stefan_utils/df_cache.py
stefan_utils/df_optimize.py
stefan_utils/logger.py
stefan_utils/py.typed
stefan_utils-0.1.0.dist-info/WHEEL
stefan_utils-0.1.0.dist-info/METADATA
stefan_utils-0.1.0.dist-info/RECORD
