Metadata-Version: 2.1
Name: stefan-utils
Version: 0.1.0
Summary: 
Author: Stefan Bader
Author-email: baderstefan@gmx.de
Requires-Python: >=3.9,<4.0
Classifier: Programming Language :: Python :: 3
Classifier: Programming Language :: Python :: 3.10
Classifier: Programming Language :: Python :: 3.9
Requires-Dist: numpy (>=1.22.3,<2.0.0)
Requires-Dist: pandas (>=1.4.1,<2.0.0)
Requires-Dist: pyarrow (>=7.0.0,<8.0.0)
Requires-Dist: pytest (>=7.1.1,<8.0.0)
Requires-Dist: python-json-logger (>=2.0.2,<3.0.0)
